[
  {
    "date": "2024-11-01T14:30:04.245000+00:00",
    "session_key": 9626,
    "lane_duration": null,
    "stop_duration": null,
    "pit_duration": null,
    "driver_number": 77,
    "meeting_key": 1249,
    "lap_number": 1
  },
  {
    "date": "2024-11-01T14:30:15.347000+00:00",
    "session_key": 9626,
    "lane_duration": null,
    "stop_duration": null,
    "pit_duration": null,
    "driver_number": 10,
    "meeting_key": 1249,
    "lap_number": 1
  },
  {
    "date": "2024-11-01T14:30:20.719000+00:00",
    "session_key": 9626,
    "lane_duration": null,
    "stop_duration": null,
    "pit_duration": null,
    "driver_number": 24,
    "meeting_key": 1249,
    "lap_number": 1
  },
  {
    "date": "2024-11-01T14:30:24.556000+00:00",
    "session_key": 9626,
    "lane_duration": null,
    "stop_duration": null,
    "pit_duration": null,
    "driver_number": 31,
    "meeting_key": 1249,
    "lap_number": 1
  },
  {
    "date": "2024-11-01T14:30:29.567000+00:00",
    "session_key": 9626,
    "lane_duration": null,
    "stop_duration": null,
    "pit_duration": null,
    "driver_number": 18,
    "meeting_key": 1249,
    "lap_number": 1
  },
  {
    "date": "2024-11-01T14:30:34.886000+00:00",
    "session_key": 9626,
    "lane_duration": null,
    "stop_duration": null,
    "pit_duration": null,
    "driver_number": 14,
    "meeting_key": 1249,
    "lap_number": 1
  },
  {
    "date": "2024-11-01T14:30:46.234000+00:00",
    "session_key": 9626,
    "lane_duration": null,
    "stop_duration": null,
    "pit_duration": null,
    "driver_number": 50,
    "meeting_key": 1249,
    "lap_number": 1
  },
  {
    "date": "2024-11-01T14:31:00.151000+00:00",
    "session_key": 9626,
    "lane_duration": null,
    "stop_duration": null,
    "pit_duration": null,
    "driver_number": 81,
    "meeting_key": 1249,
    "lap_number": 1
  },
  {
    "date": "2024-11-01T14:31:04.355000+00:00",
    "session_key": 9626,
    "lane_duration": null,
    "stop_duration": null,
    "pit_duration": null,
    "driver_number": 44,
    "meeting_key": 1249,
    "lap_number": 1
  },
  {
    "date": "2024-11-01T14:31:06.434000+00:00",
    "session_key": 9626,
    "lane_duration": null,
    "stop_duration": null,
    "pit_duration": null,
    "driver_number": 11,
    "meeting_key": 1249,
    "lap_number": 1
  },
  {
    "date": "2024-11-01T14:31:16.231000+00:00",
    "session_key": 9626,
    "lane_duration": null,
    "stop_duration": null,
    "pit_duration": null,
    "driver_number": 16,
    "meeting_key": 1249,
    "lap_number": 1
  },
  {
    "date": "2024-11-01T14:31:24.246000+00:00",
    "session_key": 9626,
    "lane_duration": null,
    "stop_duration": null,
    "pit_duration": null,
    "driver_number": 4,
    "meeting_key": 1249,
    "lap_number": 1
  },
  {
    "date": "2024-11-01T14:31:26.902000+00:00",
    "session_key": 9626,
    "lane_duration": null,
    "stop_duration": null,
    "pit_duration": null,
    "driver_number": 55,
    "meeting_key": 1249,
    "lap_number": 1
  },
  {
    "date": "2024-11-01T14:32:17.121000+00:00",
    "session_key": 9626,
    "lane_duration": null,
    "stop_duration": null,
    "pit_duration": null,
    "driver_number": 63,
    "meeting_key": 1249,
    "lap_number": 1
  },
  {
    "date": "2024-11-01T14:32:37.126000+00:00",
    "session_key": 9626,
    "lane_duration": null,
    "stop_duration": null,
    "pit_duration": null,
    "driver_number": 27,
    "meeting_key": 1249,
    "lap_number": 1
  },
  {
    "date": "2024-11-01T14:32:39.292000+00:00",
    "session_key": 9626,
    "lane_duration": 25.8,
    "stop_duration": null,
    "pit_duration": 25.8,
    "driver_number": 18,
    "meeting_key": 1249,
    "lap_number": 2
  },
  {
    "date": "2024-11-01T14:32:51.745000+00:00",
    "session_key": 9626,
    "lane_duration": 28.9,
    "stop_duration": null,
    "pit_duration": 28.9,
    "driver_number": 14,
    "meeting_key": 1249,
    "lap_number": 2
  },
  {
    "date": "2024-11-01T14:33:07.411000+00:00",
    "session_key": 9626,
    "lane_duration": null,
    "stop_duration": null,
    "pit_duration": null,
    "driver_number": 1,
    "meeting_key": 1249,
    "lap_number": 1
  },
  {
    "date": "2024-11-01T14:33:18.649000+00:00",
    "session_key": 9626,
    "lane_duration": null,
    "stop_duration": null,
    "pit_duration": null,
    "driver_number": 22,
    "meeting_key": 1249,
    "lap_number": 1
  },
  {
    "date": "2024-11-01T14:33:24.456000+00:00",
    "session_key": 9626,
    "lane_duration": null,
    "stop_duration": null,
    "pit_duration": null,
    "driver_number": 30,
    "meeting_key": 1249,
    "lap_number": 1
  },
  {
    "date": "2024-11-01T14:33:35.361000+00:00",
    "session_key": 9626,
    "lane_duration": null,
    "stop_duration": null,
    "pit_duration": null,
    "driver_number": 43,
    "meeting_key": 1249,
    "lap_number": 1
  },
  {
    "date": "2024-11-01T14:33:49.722000+00:00",
    "session_key": 9626,
    "lane_duration": null,
    "stop_duration": null,
    "pit_duration": null,
    "driver_number": 23,
    "meeting_key": 1249,
    "lap_number": 1
  },
  {
    "date": "2024-11-01T14:35:57.164000+00:00",
    "session_key": 9626,
    "stop_duration": null,
    "driver_number": 23,
    "meeting_key": 1249,
    "lap_number": 2,
    "pit_duration": 32.5,
    "lane_duration": 32.5
  },
  {
    "date": "2024-11-01T14:36:00.708000+00:00",
    "session_key": 9626,
    "stop_duration": null,
    "driver_number": 11,
    "meeting_key": 1249,
    "lap_number": 4,
    "pit_duration": 29.2,
    "lane_duration": 29.2
  },
  {
    "date": "2024-11-01T14:37:50.891000+00:00",
    "session_key": 9626,
    "stop_duration": null,
    "driver_number": 14,
    "meeting_key": 1249,
    "lap_number": 5,
    "pit_duration": 30.6,
    "lane_duration": 30.6
  },
  {
    "date": "2024-11-01T14:37:57.893000+00:00",
    "session_key": 9626,
    "stop_duration": null,
    "driver_number": 18,
    "meeting_key": 1249,
    "lap_number": 5,
    "pit_duration": 31.7,
    "lane_duration": 31.7
  },
  {
    "date": "2024-11-01T14:39:54.503000+00:00",
    "session_key": 9626,
    "stop_duration": null,
    "driver_number": 50,
    "meeting_key": 1249,
    "lap_number": 6,
    "pit_duration": 82.6,
    "lane_duration": 82.6
  },
  {
    "date": "2024-11-01T14:40:59.846000+00:00",
    "session_key": 9626,
    "stop_duration": null,
    "driver_number": 27,
    "meeting_key": 1249,
    "lap_number": 6,
    "pit_duration": 51.4,
    "lane_duration": 51.4
  },
  {
    "date": "2024-11-01T14:41:14.147000+00:00",
    "session_key": 9626,
    "stop_duration": null,
    "driver_number": 11,
    "meeting_key": 1249,
    "lap_number": 7,
    "pit_duration": 35.2,
    "lane_duration": 35.2
  },
  {
    "date": "2024-11-01T14:41:29.604000+00:00",
    "session_key": 9626,
    "stop_duration": null,
    "driver_number": 1,
    "meeting_key": 1249,
    "lap_number": 6,
    "pit_duration": 25.4,
    "lane_duration": 25.4
  },
  {
    "date": "2024-11-01T14:42:12.904000+00:00",
    "session_key": 9626,
    "stop_duration": null,
    "driver_number": 43,
    "meeting_key": 1249,
    "lap_number": 6,
    "pit_duration": 19.8,
    "lane_duration": 19.8
  },
  {
    "date": "2024-11-01T14:43:18.926000+00:00",
    "session_key": 9626,
    "stop_duration": null,
    "driver_number": 16,
    "meeting_key": 1249,
    "lap_number": 8,
    "pit_duration": 18.6,
    "lane_duration": 18.6
  },
  {
    "date": "2024-11-01T14:44:36.183000+00:00",
    "session_key": 9626,
    "stop_duration": null,
    "driver_number": 55,
    "meeting_key": 1249,
    "lap_number": 9,
    "pit_duration": 30.7,
    "lane_duration": 30.7
  },
  {
    "date": "2024-11-01T14:45:52.874000+00:00",
    "session_key": 9626,
    "stop_duration": null,
    "driver_number": 23,
    "meeting_key": 1249,
    "lap_number": 8,
    "pit_duration": 18.5,
    "lane_duration": 18.5
  },
  {
    "date": "2024-11-01T14:47:01.407000+00:00",
    "session_key": 9626,
    "stop_duration": null,
    "driver_number": 22,
    "meeting_key": 1249,
    "lap_number": 9,
    "pit_duration": 18.2,
    "lane_duration": 18.2
  },
  {
    "date": "2024-11-01T14:47:11.852000+00:00",
    "session_key": 9626,
    "stop_duration": null,
    "driver_number": 30,
    "meeting_key": 1249,
    "lap_number": 9,
    "pit_duration": 34.1,
    "lane_duration": 34.1
  },
  {
    "date": "2024-11-01T14:47:42.888000+00:00",
    "session_key": 9626,
    "stop_duration": null,
    "driver_number": 43,
    "meeting_key": 1249,
    "lap_number": 9,
    "pit_duration": 18.0,
    "lane_duration": 18.0
  },
  {
    "date": "2024-11-01T14:49:06.142000+00:00",
    "session_key": 9626,
    "stop_duration": null,
    "driver_number": 77,
    "meeting_key": 1249,
    "lap_number": 6,
    "pit_duration": 696.2,
    "lane_duration": 696.2
  },
  {
    "date": "2024-11-01T14:53:51.967000+00:00",
    "session_key": 9626,
    "stop_duration": null,
    "driver_number": 81,
    "meeting_key": 1249,
    "lap_number": 8,
    "pit_duration": 731.9,
    "lane_duration": 731.9
  },
  {
    "date": "2024-11-01T14:54:10.447000+00:00",
    "session_key": 9626,
    "stop_duration": null,
    "driver_number": 4,
    "meeting_key": 1249,
    "lap_number": 9,
    "pit_duration": 635.6,
    "lane_duration": 635.6
  },
  {
    "date": "2024-11-01T14:54:36.026000+00:00",
    "session_key": 9626,
    "stop_duration": null,
    "driver_number": 50,
    "meeting_key": 1249,
    "lap_number": 9,
    "pit_duration": 600.7,
    "lane_duration": 600.7
  },
  {
    "date": "2024-11-01T14:54:41.427000+00:00",
    "session_key": 9626,
    "stop_duration": null,
    "driver_number": 1,
    "meeting_key": 1249,
    "lap_number": 10,
    "pit_duration": 429.2,
    "lane_duration": 429.2
  },
  {
    "date": "2024-11-01T14:55:06.568000+00:00",
    "session_key": 9626,
    "stop_duration": null,
    "driver_number": 44,
    "meeting_key": 1249,
    "lap_number": 10,
    "pit_duration": 489.8,
    "lane_duration": 489.8
  },
  {
    "date": "2024-11-01T14:56:15.013000+00:00",
    "session_key": 9626,
    "stop_duration": null,
    "driver_number": 43,
    "meeting_key": 1249,
    "lap_number": 12,
    "pit_duration": 226.0,
    "lane_duration": 226.0
  },
  {
    "date": "2024-11-01T14:56:37.826000+00:00",
    "session_key": 9626,
    "stop_duration": null,
    "driver_number": 14,
    "meeting_key": 1249,
    "lap_number": 9,
    "pit_duration": 750.7,
    "lane_duration": 750.7
  },
  {
    "date": "2024-11-01T14:56:42.385000+00:00",
    "session_key": 9626,
    "stop_duration": null,
    "driver_number": 30,
    "meeting_key": 1249,
    "lap_number": 12,
    "pit_duration": 302.9,
    "lane_duration": 302.9
  },
  {
    "date": "2024-11-01T14:56:52.865000+00:00",
    "session_key": 9626,
    "stop_duration": null,
    "driver_number": 18,
    "meeting_key": 1249,
    "lap_number": 10,
    "pit_duration": 644.0,
    "lane_duration": 644.0
  },
  {
    "date": "2024-11-01T14:57:11.768000+00:00",
    "session_key": 9626,
    "stop_duration": null,
    "driver_number": 22,
    "meeting_key": 1249,
    "lap_number": 11,
    "pit_duration": 420.7,
    "lane_duration": 420.7
  },
  {
    "date": "2024-11-01T14:57:46.968000+00:00",
    "session_key": 9626,
    "stop_duration": null,
    "driver_number": 27,
    "meeting_key": 1249,
    "lap_number": 12,
    "pit_duration": 421.6,
    "lane_duration": 421.6
  },
  {
    "date": "2024-11-01T14:58:05.229000+00:00",
    "session_key": 9626,
    "stop_duration": null,
    "driver_number": 23,
    "meeting_key": 1249,
    "lap_number": 11,
    "pit_duration": 454.2,
    "lane_duration": 454.2
  },
  {
    "date": "2024-11-01T14:58:56.435000+00:00",
    "session_key": 9626,
    "stop_duration": null,
    "driver_number": 81,
    "meeting_key": 1249,
    "lap_number": 11,
    "pit_duration": 18.1,
    "lane_duration": 18.1
  },
  {
    "date": "2024-11-01T14:59:27.081000+00:00",
    "session_key": 9626,
    "stop_duration": null,
    "driver_number": 10,
    "meeting_key": 1249,
    "lap_number": 8,
    "pit_duration": 1054.6,
    "lane_duration": 1054.6
  },
  {
    "date": "2024-11-01T14:59:29.054000+00:00",
    "session_key": 9626,
    "stop_duration": null,
    "driver_number": 77,
    "meeting_key": 1249,
    "lap_number": 13,
    "pit_duration": 33.7,
    "lane_duration": 33.7
  },
  {
    "date": "2024-11-01T15:00:14.675000+00:00",
    "session_key": 9626,
    "stop_duration": null,
    "driver_number": 11,
    "meeting_key": 1249,
    "lap_number": 12,
    "pit_duration": 644.1,
    "lane_duration": 644.1
  },
  {
    "date": "2024-11-01T15:00:48.966000+00:00",
    "session_key": 9626,
    "stop_duration": null,
    "driver_number": 50,
    "meeting_key": 1249,
    "lap_number": 12,
    "pit_duration": 80.6,
    "lane_duration": 80.6
  },
  {
    "date": "2024-11-01T15:01:50.374000+00:00",
    "session_key": 9626,
    "stop_duration": null,
    "driver_number": 31,
    "meeting_key": 1249,
    "lap_number": 11,
    "pit_duration": 890.3,
    "lane_duration": 890.3
  },
  {
    "date": "2024-11-01T15:02:28.755000+00:00",
    "session_key": 9626,
    "stop_duration": null,
    "driver_number": 16,
    "meeting_key": 1249,
    "lap_number": 13,
    "pit_duration": 665.2,
    "lane_duration": 665.2
  },
  {
    "date": "2024-11-01T15:03:22.929000+00:00",
    "session_key": 9626,
    "stop_duration": null,
    "driver_number": 24,
    "meeting_key": 1249,
    "lap_number": 11,
    "pit_duration": 981.2,
    "lane_duration": 981.2
  },
  {
    "date": "2024-11-01T15:03:58.905000+00:00",
    "session_key": 9626,
    "stop_duration": null,
    "driver_number": 55,
    "meeting_key": 1249,
    "lap_number": 13,
    "pit_duration": 758.5,
    "lane_duration": 758.5
  },
  {
    "date": "2024-11-01T15:05:14.228000+00:00",
    "session_key": 9626,
    "stop_duration": null,
    "driver_number": 30,
    "meeting_key": 1249,
    "lap_number": 18,
    "pit_duration": 18.2,
    "lane_duration": 18.2
  },
  {
    "date": "2024-11-01T15:06:35.532000+00:00",
    "session_key": 9626,
    "stop_duration": null,
    "driver_number": 63,
    "meeting_key": 1249,
    "lap_number": 9,
    "pit_duration": 1278.5,
    "lane_duration": 1278.5
  },
  {
    "date": "2024-11-01T15:09:27.009000+00:00",
    "session_key": 9626,
    "stop_duration": null,
    "driver_number": 4,
    "meeting_key": 1249,
    "lap_number": 19,
    "pit_duration": 26.2,
    "lane_duration": 26.2
  },
  {
    "date": "2024-11-01T15:10:12.499000+00:00",
    "session_key": 9626,
    "stop_duration": null,
    "driver_number": 23,
    "meeting_key": 1249,
    "lap_number": 20,
    "pit_duration": 22.1,
    "lane_duration": 22.1
  },
  {
    "date": "2024-11-01T15:13:46.653000+00:00",
    "session_key": 9626,
    "stop_duration": null,
    "driver_number": 44,
    "meeting_key": 1249,
    "lap_number": 16,
    "pit_duration": 478.2,
    "lane_duration": 478.2
  },
  {
    "date": "2024-11-01T15:16:54.168000+00:00",
    "session_key": 9626,
    "stop_duration": null,
    "driver_number": 63,
    "meeting_key": 1249,
    "lap_number": 12,
    "pit_duration": 362.9,
    "lane_duration": 362.9
  },
  {
    "date": "2024-11-01T15:18:03.536000+00:00",
    "session_key": 9626,
    "stop_duration": null,
    "driver_number": 43,
    "meeting_key": 1249,
    "lap_number": 23,
    "pit_duration": 442.5,
    "lane_duration": 442.5
  },
  {
    "date": "2024-11-01T15:18:35.914000+00:00",
    "session_key": 9626,
    "stop_duration": null,
    "driver_number": 16,
    "meeting_key": 1249,
    "lap_number": 22,
    "pit_duration": 248.3,
    "lane_duration": 248.3
  },
  {
    "date": "2024-11-01T15:19:22.084000+00:00",
    "session_key": 9626,
    "stop_duration": null,
    "driver_number": 24,
    "meeting_key": 1249,
    "lap_number": 19,
    "pit_duration": 313.9,
    "lane_duration": 313.9
  },
  {
    "date": "2024-11-01T15:19:36.631000+00:00",
    "session_key": 9626,
    "stop_duration": null,
    "driver_number": 50,
    "meeting_key": 1249,
    "lap_number": 23,
    "pit_duration": 224.0,
    "lane_duration": 224.0
  },
  {
    "date": "2024-11-01T15:19:42.802000+00:00",
    "session_key": 9626,
    "stop_duration": null,
    "driver_number": 23,
    "meeting_key": 1249,
    "lap_number": 21,
    "pit_duration": 488.9,
    "lane_duration": 488.9
  },
  {
    "date": "2024-11-01T15:19:52.397000+00:00",
    "session_key": 9626,
    "stop_duration": null,
    "driver_number": 55,
    "meeting_key": 1249,
    "lap_number": 23,
    "pit_duration": 137.0,
    "lane_duration": 137.0
  },
  {
    "date": "2024-11-01T15:20:36.851000+00:00",
    "session_key": 9626,
    "stop_duration": null,
    "driver_number": 30,
    "meeting_key": 1249,
    "lap_number": 19,
    "pit_duration": 818.1,
    "lane_duration": 818.1
  },
  {
    "date": "2024-11-01T15:20:40.211000+00:00",
    "session_key": 9626,
    "stop_duration": null,
    "driver_number": 81,
    "meeting_key": 1249,
    "lap_number": 23,
    "pit_duration": 363.6,
    "lane_duration": 363.6
  },
  {
    "date": "2024-11-01T15:21:10.590000+00:00",
    "session_key": 9626,
    "stop_duration": null,
    "driver_number": 18,
    "meeting_key": 1249,
    "lap_number": 22,
    "pit_duration": 385.7,
    "lane_duration": 385.7
  },
  {
    "date": "2024-11-01T15:21:17.532000+00:00",
    "session_key": 9626,
    "stop_duration": null,
    "driver_number": 77,
    "meeting_key": 1249,
    "lap_number": 22,
    "pit_duration": 598.3,
    "lane_duration": 598.3
  },
  {
    "date": "2024-11-01T15:21:32.382000+00:00",
    "session_key": 9626,
    "stop_duration": null,
    "driver_number": 27,
    "meeting_key": 1249,
    "lap_number": 20,
    "pit_duration": 751.9,
    "lane_duration": 751.9
  },
  {
    "date": "2024-11-01T15:21:44.049000+00:00",
    "session_key": 9626,
    "stop_duration": null,
    "driver_number": 4,
    "meeting_key": 1249,
    "lap_number": 23,
    "pit_duration": 429.1,
    "lane_duration": 429.1
  },
  {
    "date": "2024-11-01T15:21:47.055000+00:00",
    "session_key": 9626,
    "stop_duration": null,
    "driver_number": 31,
    "meeting_key": 1249,
    "lap_number": 20,
    "pit_duration": 456.5,
    "lane_duration": 456.5
  },
  {
    "date": "2024-11-01T15:22:00.834000+00:00",
    "session_key": 9626,
    "stop_duration": null,
    "driver_number": 10,
    "meeting_key": 1249,
    "lap_number": 21,
    "pit_duration": 269.3,
    "lane_duration": 269.3
  },
  {
    "date": "2024-11-01T15:22:16.470000+00:00",
    "session_key": 9626,
    "stop_duration": null,
    "driver_number": 14,
    "meeting_key": 1249,
    "lap_number": 21,
    "pit_duration": 512.2,
    "lane_duration": 512.2
  },
  {
    "date": "2024-11-01T15:23:22.047000+00:00",
    "session_key": 9626,
    "stop_duration": null,
    "driver_number": 43,
    "meeting_key": 1249,
    "lap_number": 26,
    "pit_duration": 20.3,
    "lane_duration": 20.3
  },
  {
    "date": "2024-11-01T15:24:13.390000+00:00",
    "session_key": 9626,
    "stop_duration": null,
    "driver_number": 11,
    "meeting_key": 1249,
    "lap_number": 23,
    "pit_duration": 578.9,
    "lane_duration": 578.9
  },
  {
    "date": "2024-11-01T15:24:33.014000+00:00",
    "session_key": 9626,
    "stop_duration": null,
    "driver_number": 22,
    "meeting_key": 1249,
    "lap_number": 20,
    "pit_duration": 926.5,
    "lane_duration": 926.5
  },
  {
    "date": "2024-11-01T15:24:48.533000+00:00",
    "session_key": 9626,
    "stop_duration": null,
    "driver_number": 24,
    "meeting_key": 1249,
    "lap_number": 22,
    "pit_duration": 40.1,
    "lane_duration": 40.1
  },
  {
    "date": "2024-11-01T15:24:51.139000+00:00",
    "session_key": 9626,
    "stop_duration": null,
    "driver_number": 23,
    "meeting_key": 1249,
    "lap_number": 24,
    "pit_duration": 24.0,
    "lane_duration": 24.0
  },
  {
    "date": "2024-11-01T15:25:24.013000+00:00",
    "session_key": 9626,
    "stop_duration": null,
    "driver_number": 55,
    "meeting_key": 1249,
    "lap_number": 26,
    "pit_duration": 34.8,
    "lane_duration": 34.8
  },
  {
    "date": "2024-11-01T15:25:25.779000+00:00",
    "session_key": 9626,
    "stop_duration": null,
    "driver_number": 30,
    "meeting_key": 1249,
    "lap_number": 22,
    "pit_duration": 28.3,
    "lane_duration": 28.3
  },
  {
    "date": "2024-11-01T15:25:36.059000+00:00",
    "session_key": 9626,
    "stop_duration": null,
    "driver_number": 81,
    "meeting_key": 1249,
    "lap_number": 26,
    "pit_duration": 18.1,
    "lane_duration": 18.1
  },
  {
    "date": "2024-11-01T15:25:40.568000+00:00",
    "session_key": 9626,
    "stop_duration": null,
    "driver_number": 1,
    "meeting_key": 1249,
    "lap_number": 26,
    "pit_duration": 620.7,
    "lane_duration": 620.7
  },
  {
    "date": "2024-11-01T15:25:46.178000+00:00",
    "session_key": 9626,
    "stop_duration": null,
    "driver_number": 50,
    "meeting_key": 1249,
    "lap_number": 26,
    "pit_duration": 90.3,
    "lane_duration": 90.3
  },
  {
    "date": "2024-11-01T15:26:26.612000+00:00",
    "session_key": 9626,
    "stop_duration": null,
    "driver_number": 77,
    "meeting_key": 1249,
    "lap_number": 25,
    "pit_duration": 18.2,
    "lane_duration": 18.2
  },
  {
    "date": "2024-11-01T15:27:00.916000+00:00",
    "session_key": 9626,
    "stop_duration": null,
    "driver_number": 4,
    "meeting_key": 1249,
    "lap_number": 26,
    "pit_duration": 26.3,
    "lane_duration": 26.3
  },
  {
    "date": "2024-11-01T15:27:13.817000+00:00",
    "session_key": 9626,
    "stop_duration": null,
    "driver_number": 31,
    "meeting_key": 1249,
    "lap_number": 23,
    "pit_duration": 20.6,
    "lane_duration": 20.6
  },
  {
    "date": "2024-11-01T15:27:18.873000+00:00",
    "session_key": 9626,
    "stop_duration": null,
    "driver_number": 43,
    "meeting_key": 1249,
    "lap_number": 28,
    "pit_duration": 26.5,
    "lane_duration": 26.5
  },
  {
    "date": "2024-11-01T15:27:28.059000+00:00",
    "session_key": 9626,
    "stop_duration": null,
    "driver_number": 10,
    "meeting_key": 1249,
    "lap_number": 24,
    "pit_duration": 31.9,
    "lane_duration": 31.9
  },
  {
    "date": "2024-11-01T15:27:54.087000+00:00",
    "session_key": 9626,
    "stop_duration": null,
    "driver_number": 27,
    "meeting_key": 1249,
    "lap_number": 23,
    "pit_duration": 90.9,
    "lane_duration": 90.9
  },
  {
    "date": "2024-11-01T15:28:55.375000+00:00",
    "session_key": 9626,
    "stop_duration": null,
    "driver_number": 1,
    "meeting_key": 1249,
    "lap_number": 28,
    "pit_duration": 25.0,
    "lane_duration": 25.0
  },
  {
    "date": "2024-11-01T15:28:57.333000+00:00",
    "session_key": 9626,
    "stop_duration": null,
    "driver_number": 23,
    "meeting_key": 1249,
    "lap_number": 26,
    "pit_duration": 25.8,
    "lane_duration": 25.8
  },
  {
    "date": "2024-11-01T15:29:07.797000+00:00",
    "session_key": 9626,
    "stop_duration": null,
    "driver_number": 14,
    "meeting_key": 1249,
    "lap_number": 24,
    "pit_duration": 123.1,
    "lane_duration": 123.1
  },
  {
    "date": "2024-11-01T15:29:15.267000+00:00",
    "session_key": 9626,
    "stop_duration": null,
    "driver_number": 11,
    "meeting_key": 1249,
    "lap_number": 26,
    "pit_duration": 31.5,
    "lane_duration": 31.5
  },
  {
    "date": "2024-11-01T15:29:24.585000+00:00",
    "session_key": 9626,
    "stop_duration": null,
    "driver_number": 43,
    "meeting_key": 1249,
    "lap_number": 29,
    "pit_duration": 18.5,
    "lane_duration": 18.5
  },
  {
    "date": "2024-11-01T15:29:39.460000+00:00",
    "session_key": 9626,
    "stop_duration": null,
    "driver_number": 22,
    "meeting_key": 1249,
    "lap_number": 23,
    "pit_duration": 27.6,
    "lane_duration": 27.6
  }
]